client/VER.py
client/__init__.py
client/bgtc.py
client/cli.py
client/main.py
dgt_sdk/__init__.py
dgt_sdk/consensus/__init__.py
dgt_sdk/consensus/driver.py
dgt_sdk/consensus/engine.py
dgt_sdk/consensus/exceptions.py
dgt_sdk/consensus/service.py
dgt_sdk/consensus/zmq_driver.py
dgt_sdk/consensus/zmq_service.py
dgt_sdk/messaging/__init__.py
dgt_sdk/messaging/exceptions.py
dgt_sdk/messaging/future.py
dgt_sdk/messaging/stream.py
dgt_sdk/processor/__init__.py
dgt_sdk/processor/config.py
dgt_sdk/processor/context.py
dgt_sdk/processor/core.py
dgt_sdk/processor/exceptions.py
dgt_sdk/processor/handler.py
dgt_sdk/processor/log.py
dgt_sdk/protobuf/__init__.py
dgt_sdk/protobuf/authorization_pb2.py
dgt_sdk/protobuf/batch_pb2.py
dgt_sdk/protobuf/bgx_validator_registry_pb2.py
dgt_sdk/protobuf/block_pb2.py
dgt_sdk/protobuf/client_batch_pb2.py
dgt_sdk/protobuf/client_batch_submit_pb2.py
dgt_sdk/protobuf/client_block_pb2.py
dgt_sdk/protobuf/client_event_pb2.py
dgt_sdk/protobuf/client_heads_pb2.py
dgt_sdk/protobuf/client_list_control_pb2.py
dgt_sdk/protobuf/client_peers_pb2.py
dgt_sdk/protobuf/client_receipt_pb2.py
dgt_sdk/protobuf/client_state_pb2.py
dgt_sdk/protobuf/client_status_pb2.py
dgt_sdk/protobuf/client_topology_pb2.py
dgt_sdk/protobuf/client_transaction_pb2.py
dgt_sdk/protobuf/consensus_pb2.py
dgt_sdk/protobuf/events_pb2.py
dgt_sdk/protobuf/genesis_pb2.py
dgt_sdk/protobuf/identity_pb2.py
dgt_sdk/protobuf/merkle_pb2.py
dgt_sdk/protobuf/network_pb2.py
dgt_sdk/protobuf/pbft_consensus_pb2.py
dgt_sdk/protobuf/processor_pb2.py
dgt_sdk/protobuf/setting_pb2.py
dgt_sdk/protobuf/state_context_pb2.py
dgt_sdk/protobuf/transaction_pb2.py
dgt_sdk/protobuf/transaction_receipt_pb2.py
dgt_sdk/protobuf/validator_pb2.py
dgt_signing/__init__.py
dgt_signing/core.py
dgt_signing/open_crypto.py
dgt_signing/secp256k1.py
BGT_Client-1.0.2.dist-info/LICENSE.txt
BGT_Client-1.0.2.dist-info/METADATA
BGT_Client-1.0.2.dist-info/WHEEL
BGT_Client-1.0.2.dist-info/entry_points.txt
BGT_Client-1.0.2.dist-info/top_level.txt
BGT_Client-1.0.2.dist-info/RECORD
